ISRSpectrum/ISRSpectrum.py
ISRSpectrum/__init__.py
ISRSpectrum/_version.py
ISRSpectrum/collision_calc.py
ISRSpectrum/ion2ion.csv
ISRSpectrum/ion2neu.csv
ISRSpectrum/plasmaline.py
ISRSpectrum/plugins/__init__.py
ISRSpectrum/plugins/gord_default.py
ISRSpectrum/plugins/gord_simple.py
ISRSpectrum/plugins/mathutils.py
isrspectrum-4.3.data/scripts/find_gord_plugs.py
isrspectrum-4.3.dist-info/licenses/LICENSE.md
isrspectrum-4.3.dist-info/METADATA
isrspectrum-4.3.dist-info/WHEEL
isrspectrum-4.3.dist-info/top_level.txt
isrspectrum-4.3.dist-info/RECORD
