Metadata-Version: 2.4
Name: ISRSpectrum
Version: 4.3
Summary: Creates ISR Spectrums
Home-page: https://github.com/jswoboda/ISRSpectrum
Author: John Swoboda
Requires-Python: >=3
License-File: LICENSE.md
Requires-Dist: nose
Requires-Dist: six
Requires-Dist: numpy
Requires-Dist: scipy
Requires-Dist: pandas
Requires-Dist: seaborn
Provides-Extra: plot
Requires-Dist: matplotlib; extra == "plot"
Requires-Dist: jupyter; extra == "plot"
Requires-Dist: seaborn; extra == "plot"
Dynamic: author
Dynamic: description
Dynamic: description-content-type
Dynamic: home-page
Dynamic: license-file
Dynamic: provides-extra
Dynamic: requires-dist
Dynamic: requires-python
Dynamic: summary
